{
    "EpisodeId": 142392,
    "StoryType": 3,
    "Order": 2,
    "Prev": 142391,
    "Next": null,
    "Chapter": "竜騎兵は妹の為、立ち上がり",
    "Title": "楽園の見届け人",
    "EpisodeDetail": [
        {
            "Id": 142392001,
            "EpisodeMasterId": 142392,
            "Order": 1,
            "GroupOrder": 1,
            "SpeakerName": "初魅",
            "FontSize": 2,
            "Phrase": "んー……っ。",
            "BackgroundImageFileName": "1600",
            "BgmFileName": "403",
            "VoiceFileName": "1423920010",
            "CharacterMotions": [
                {
                    "slotNumber": 1,
                    "FacialExpressionMasterId": 79,
                    "BodyMotionMasterId": 20,
                    "LipSyncMasterId": 4,
                    "SpineId": 20103,
                    "CharacterAppearanceType": 0,
                    "CharacterPosition": 3,
                    "CharacterLayerType": 1,
                    "SpineSize": 2
                }
            ],
            "SpeakerIconId": "201"
        },
        {
            "Id": 142392002,
            "EpisodeMasterId": 142392,
            "Order": 1,
            "GroupOrder": 2,
            "SpeakerName": "初魅",
            "FontSize": 2,
            "Phrase": "（次回の公演に向けて、演出の方針なども纏め終えたし……。/n　今日はひとまず一段落ついたな）",
            "VoiceFileName": "1423920020",
            "CharacterMotions": [
                {
                    "slotNumber": 1,
                    "FacialExpressionMasterId": 105,
                    "BodyMotionMasterId": 11,
                    "SpineId": 0,
                    "CharacterAppearanceType": 0,
                    "CharacterPosition": 3,
                    "CharacterLayerType": 1,
                    "SpineSize": 2
                }
            ],
            "SpeakerIconId": "201"
        },
        {
            "Id": 142392003,
            "EpisodeMasterId": 142392,
            "Order": 1,
            "GroupOrder": 3,
            "SpeakerName": "容",
            "FontSize": 2,
            "Phrase": "あ、初魅。/nちょうど部屋まで様子を見に行こうと思ってたんだ。",
            "VoiceFileName": "1423920030",
            "CharacterMotions": [
                {
                    "slotNumber": 1,
                    "SpineId": 0,
                    "CharacterAppearanceType": 0,
                    "CharacterPosition": 2,
                    "CharacterLayerType": 1,
                    "SpineSize": 2
                },
                {
                    "slotNumber": 2,
                    "FacialExpressionMasterId": 103,
                    "BodyMotionMasterId": 12,
                    "LipSyncMasterId": 1,
                    "SpineId": 20403,
                    "CharacterAppearanceType": 0,
                    "CharacterPosition": 4,
                    "CharacterLayerType": 1,
                    "SpineSize": 2
                }
            ],
            "SpeakerIconId": "204"
        },
        {
            "Id": 142392004,
            "EpisodeMasterId": 142392,
            "Order": 1,
            "GroupOrder": 4,
            "SpeakerName": "初魅",
            "FontSize": 2,
            "Phrase": "なんだ、私を気にかけてくれていたのか。/n相変わらず優しいな、お前は。",
            "VoiceFileName": "1423920040",
            "CharacterMotions": [
                {
                    "slotNumber": 1,
                    "FacialExpressionMasterId": 202,
                    "BodyMotionMasterId": 15,
                    "LipSyncMasterId": 1,
                    "SpineId": 0,
                    "CharacterAppearanceType": 0,
                    "CharacterPosition": 2,
                    "CharacterLayerType": 1,
                    "SpineSize": 2
                },
                {
                    "slotNumber": 2,
                    "SpineId": 0,
                    "CharacterAppearanceType": 0,
                    "CharacterPosition": 4,
                    "CharacterLayerType": 1,
                    "SpineSize": 2
                }
            ],
            "SpeakerIconId": "201"
        },
        {
            "Id": 142392005,
            "EpisodeMasterId": 142392,
            "Order": 1,
            "GroupOrder": 5,
            "SpeakerName": "容",
            "FontSize": 2,
            "Phrase": "まぁね。公演の方針が固まってから、何かと忙しくなったからさ。/n根を詰めすぎていないか、ちょっと心配だったんだ。",
            "VoiceFileName": "1423920050",
            "CharacterMotions": [
                {
                    "slotNumber": 1,
                    "SpineId": 0,
                    "CharacterAppearanceType": 0,
                    "CharacterPosition": 2,
                    "CharacterLayerType": 1,
                    "SpineSize": 2
                },
                {
                    "slotNumber": 2,
                    "FacialExpressionMasterId": 105,
                    "BodyMotionMasterId": 20,
                    "LipSyncMasterId": 1,
                    "SpineId": 0,
                    "CharacterAppearanceType": 0,
                    "CharacterPosition": 4,
                    "CharacterLayerType": 1,
                    "SpineSize": 2
                }
            ],
            "SpeakerIconId": "204"
        },
        {
            "Id": 142392006,
            "EpisodeMasterId": 142392,
            "Order": 1,
            "GroupOrder": 6,
            "SpeakerName": "初魅",
            "FontSize": 2,
            "Phrase": "どうかな、見方によっては無理していると言われるだろう。/nだがむしろ私は、やる気に燃えているよ。",
            "VoiceFileName": "1423920060",
            "CharacterMotions": [
                {
                    "slotNumber": 1,
                    "FacialExpressionMasterId": 103,
                    "BodyMotionMasterId": 14,
                    "LipSyncMasterId": 1,
                    "SpineId": 0,
                    "CharacterAppearanceType": 0,
                    "CharacterPosition": 2,
                    "CharacterLayerType": 1,
                    "SpineSize": 2
                },
                {
                    "slotNumber": 2,
                    "SpineId": 0,
                    "CharacterAppearanceType": 0,
                    "CharacterPosition": 4,
                    "CharacterLayerType": 1,
                    "SpineSize": 2
                }
            ],
            "SpeakerIconId": "201"
        },
        {
            "Id": 142392007,
            "EpisodeMasterId": 142392,
            "Order": 1,
            "GroupOrder": 7,
            "SpeakerName": "容",
            "FontSize": 2,
            "Phrase": "そう……でも、実際大変なのは事実でしょ。/nよければこの後、一緒にご飯でもどう？",
            "VoiceFileName": "1423920070",
            "CharacterMotions": [
                {
                    "slotNumber": 1,
                    "SpineId": 0,
                    "CharacterAppearanceType": 0,
                    "CharacterPosition": 2,
                    "CharacterLayerType": 1,
                    "SpineSize": 2
                },
                {
                    "slotNumber": 2,
                    "FacialExpressionMasterId": 103,
                    "BodyMotionMasterId": 11,
                    "LipSyncMasterId": 1,
                    "SpineId": 0,
                    "CharacterAppearanceType": 0,
                    "CharacterPosition": 4,
                    "CharacterLayerType": 1,
                    "SpineSize": 2
                }
            ],
            "SpeakerIconId": "204"
        },
        {
            "Id": 142392008,
            "EpisodeMasterId": 142392,
            "Order": 1,
            "GroupOrder": 8,
            "SpeakerName": "初魅",
            "FontSize": 2,
            "Phrase": "いいな、容からの誘いはいつでも歓迎だ。/nちょうど考えもまとまってきたところだったしな。",
            "VoiceFileName": "1423920080",
            "CharacterMotions": [
                {
                    "slotNumber": 1,
                    "FacialExpressionMasterId": 202,
                    "HeadMotionMasterId": 1,
                    "BodyMotionMasterId": 15,
                    "LipSyncMasterId": 1,
                    "SpineId": 0,
                    "CharacterAppearanceType": 0,
                    "CharacterPosition": 2,
                    "CharacterLayerType": 1,
                    "SpineSize": 2
                },
                {
                    "slotNumber": 2,
                    "SpineId": 0,
                    "CharacterAppearanceType": 0,
                    "CharacterPosition": 4,
                    "CharacterLayerType": 1,
                    "SpineSize": 2
                }
            ],
            "SpeakerIconId": "201"
        },
        {
            "Id": 142392009,
            "EpisodeMasterId": 142392,
            "Order": 1,
            "GroupOrder": 9,
            "FontSize": 2,
            "Phrase": "",
            "BackgroundImageFileFadeType": 1,
            "CharacterMotions": [],
            "FadeValue1": 0.20000000298023224,
            "FadeValue2": 0.30000001192092896,
            "FadeValue3": 0.20000000298023224
        },
        {
            "Id": 142392010,
            "EpisodeMasterId": 142392,
            "Order": 1,
            "GroupOrder": 10,
            "SpeakerName": "初魅",
            "FontSize": 2,
            "Phrase": "……という訳だ、/nまた話を聞いてもらうことになるかもしれないが、構わないか？",
            "VoiceFileName": "1423920090",
            "CharacterMotions": [
                {
                    "slotNumber": 1,
                    "FacialExpressionMasterId": 103,
                    "BodyMotionMasterId": 15,
                    "LipSyncMasterId": 1,
                    "SpineId": 20103,
                    "CharacterAppearanceType": 0,
                    "CharacterPosition": 3,
                    "CharacterLayerType": 1,
                    "SpineSize": 2
                }
            ],
            "SpeakerIconId": "201"
        },
        {
            "Id": 142392011,
            "EpisodeMasterId": 142392,
            "Order": 1,
            "GroupOrder": 11,
            "SpeakerName": "容",
            "FontSize": 2,
            "Phrase": "アタシで良ければ、お安い御用だよ。/n……これじゃあEdenの相談窓口って呼ばれる日も近いねぇ。",
            "VoiceFileName": "1423920100",
            "CharacterMotions": [
                {
                    "slotNumber": 1,
                    "SpineId": 0,
                    "CharacterAppearanceType": 0,
                    "CharacterPosition": 2,
                    "CharacterLayerType": 1,
                    "SpineSize": 2
                },
                {
                    "slotNumber": 2,
                    "FacialExpressionMasterId": 202,
                    "BodyMotionMasterId": 13,
                    "LipSyncMasterId": 1,
                    "SpineId": 20403,
                    "CharacterAppearanceType": 0,
                    "CharacterPosition": 4,
                    "CharacterLayerType": 1,
                    "SpineSize": 2
                }
            ],
            "SpeakerIconId": "204"
        },
        {
            "Id": 142392012,
            "EpisodeMasterId": 142392,
            "Order": 1,
            "GroupOrder": 12,
            "SpeakerName": "初魅",
            "FontSize": 2,
            "Phrase": "なかなか悪くない肩書じゃないか。/n皆から慕われている証拠だ。",
            "VoiceFileName": "1423920110",
            "CharacterMotions": [
                {
                    "slotNumber": 1,
                    "BodyMotionMasterId": 7,
                    "LipSyncMasterId": 1,
                    "SpineId": 0,
                    "CharacterAppearanceType": 0,
                    "CharacterPosition": 2,
                    "CharacterLayerType": 1,
                    "SpineSize": 2
                },
                {
                    "slotNumber": 2,
                    "SpineId": 0,
                    "CharacterAppearanceType": 0,
                    "CharacterPosition": 4,
                    "CharacterLayerType": 1,
                    "SpineSize": 2
                }
            ],
            "SpeakerIconId": "201"
        },
        {
            "Id": 142392013,
            "EpisodeMasterId": 142392,
            "Order": 1,
            "GroupOrder": 13,
            "SpeakerName": "容",
            "FontSize": 2,
            "Phrase": "はは、物は言いようってやつだけどね。",
            "VoiceFileName": "1423920120",
            "CharacterMotions": [
                {
                    "slotNumber": 1,
                    "SpineId": 0,
                    "CharacterAppearanceType": 0,
                    "CharacterPosition": 2,
                    "CharacterLayerType": 1,
                    "SpineSize": 2
                },
                {
                    "slotNumber": 2,
                    "FacialExpressionMasterId": 105,
                    "BodyMotionMasterId": 20,
                    "LipSyncMasterId": 1,
                    "SpineId": 0,
                    "CharacterAppearanceType": 0,
                    "CharacterPosition": 4,
                    "CharacterLayerType": 1,
                    "SpineSize": 2
                }
            ],
            "SpeakerIconId": "204"
        },
        {
            "Id": 142392014,
            "EpisodeMasterId": 142392,
            "Order": 1,
            "GroupOrder": 14,
            "FontSize": 2,
            "Phrase": "",
            "BackgroundImageFileName": "970",
            "BackgroundImageFileFadeType": 1,
            "CharacterMotions": [],
            "FadeValue1": 0.20000000298023224,
            "FadeValue2": 0.30000001192092896,
            "FadeValue3": 0.20000000298023224
        },
        {
            "Id": 142392015,
            "EpisodeMasterId": 142392,
            "Order": 1,
            "GroupOrder": 15,
            "SpeakerName": "初魅",
            "FontSize": 2,
            "Phrase": "ん……美味しいものを食べると、わずかに肩の力が抜けるな。/nやはり、誘って貰ってちょうど良かった。",
            "VoiceFileName": "1423920130",
            "CharacterMotions": [
                {
                    "slotNumber": 1,
                    "FacialExpressionMasterId": 103,
                    "BodyMotionMasterId": 20,
                    "LipSyncMasterId": 1,
                    "SpineId": 20101,
                    "CharacterAppearanceType": 0,
                    "CharacterPosition": 3,
                    "CharacterLayerType": 1,
                    "SpineSize": 2
                }
            ],
            "SpeakerIconId": "201"
        },
        {
            "Id": 142392016,
            "EpisodeMasterId": 142392,
            "Order": 1,
            "GroupOrder": 16,
            "SpeakerName": "容",
            "FontSize": 2,
            "Phrase": "これでもそれなりに、初魅とは長い付き合いだからね。/nそういうタイミングなんじゃないかって思ったんだ。",
            "VoiceFileName": "1423920140",
            "CharacterMotions": [
                {
                    "slotNumber": 1,
                    "SpineId": 0,
                    "CharacterAppearanceType": 0,
                    "CharacterPosition": 2,
                    "CharacterLayerType": 1,
                    "SpineSize": 2
                },
                {
                    "slotNumber": 2,
                    "FacialExpressionMasterId": 103,
                    "BodyMotionMasterId": 11,
                    "LipSyncMasterId": 1,
                    "SpineId": 20401,
                    "CharacterAppearanceType": 0,
                    "CharacterPosition": 4,
                    "CharacterLayerType": 1,
                    "SpineSize": 2
                }
            ],
            "SpeakerIconId": "204"
        },
        {
            "Id": 142392017,
            "EpisodeMasterId": 142392,
            "Order": 1,
            "GroupOrder": 17,
            "SpeakerName": "容",
            "FontSize": 2,
            "Phrase": "っていうのと、あと……。/nしぐれの為に、色々と考えてくれてありがとうね。",
            "VoiceFileName": "1423920150",
            "CharacterMotions": [
                {
                    "slotNumber": 1,
                    "SpineId": 0,
                    "CharacterAppearanceType": 0,
                    "CharacterPosition": 2,
                    "CharacterLayerType": 1,
                    "SpineSize": 2
                },
                {
                    "slotNumber": 2,
                    "FacialExpressionMasterId": 71,
                    "BodyMotionMasterId": 13,
                    "LipSyncMasterId": 1,
                    "SpineId": 0,
                    "CharacterAppearanceType": 0,
                    "CharacterPosition": 4,
                    "CharacterLayerType": 1,
                    "SpineSize": 2
                }
            ],
            "SpeakerIconId": "204"
        },
        {
            "Id": 142392018,
            "EpisodeMasterId": 142392,
            "Order": 1,
            "GroupOrder": 18,
            "SpeakerName": "容",
            "FontSize": 2,
            "Phrase": "あの子、ひとりで抱え込んでるみたいだったから……。/n心配はしてたんだけど……アタシじゃどうにも出来なくて。",
            "VoiceFileName": "1423920160",
            "CharacterMotions": [
                {
                    "slotNumber": 1,
                    "SpineId": 0,
                    "CharacterAppearanceType": 0,
                    "CharacterPosition": 2,
                    "CharacterLayerType": 1,
                    "SpineSize": 2
                },
                {
                    "slotNumber": 2,
                    "FacialExpressionMasterId": 400,
                    "BodyMotionMasterId": 25,
                    "LipSyncMasterId": 4,
                    "SpineId": 0,
                    "CharacterAppearanceType": 0,
                    "CharacterPosition": 4,
                    "CharacterLayerType": 1,
                    "SpineSize": 2
                }
            ],
            "SpeakerIconId": "204"
        },
        {
            "Id": 142392019,
            "EpisodeMasterId": 142392,
            "Order": 1,
            "GroupOrder": 19,
            "SpeakerName": "初魅",
            "FontSize": 2,
            "Phrase": "気にするな。/nしぐれは私の楽園にとって必要な役者だ。",
            "VoiceFileName": "1423920170",
            "CharacterMotions": [
                {
                    "slotNumber": 1,
                    "FacialExpressionMasterId": 103,
                    "BodyMotionMasterId": 15,
                    "LipSyncMasterId": 1,
                    "SpineId": 0,
                    "CharacterAppearanceType": 0,
                    "CharacterPosition": 2,
                    "CharacterLayerType": 1,
                    "SpineSize": 2
                },
                {
                    "slotNumber": 2,
                    "SpineId": 0,
                    "CharacterAppearanceType": 0,
                    "CharacterPosition": 4,
                    "CharacterLayerType": 1,
                    "SpineSize": 2
                }
            ],
            "SpeakerIconId": "201"
        },
        {
            "Id": 142392020,
            "EpisodeMasterId": 142392,
            "Order": 1,
            "GroupOrder": 20,
            "SpeakerName": "初魅",
            "FontSize": 2,
            "Phrase": "その役者が楽園で演じ続けたいと言うなら、/n叶えてやるのが創造主としての務めだろう。",
            "VoiceFileName": "1423920180",
            "CharacterMotions": [
                {
                    "slotNumber": 1,
                    "FacialExpressionMasterId": 71,
                    "BodyMotionMasterId": 14,
                    "LipSyncMasterId": 1,
                    "SpineId": 0,
                    "CharacterAppearanceType": 0,
                    "CharacterPosition": 2,
                    "CharacterLayerType": 1,
                    "SpineSize": 2
                },
                {
                    "slotNumber": 2,
                    "SpineId": 0,
                    "CharacterAppearanceType": 0,
                    "CharacterPosition": 4,
                    "CharacterLayerType": 1,
                    "SpineSize": 2
                }
            ],
            "SpeakerIconId": "201"
        },
        {
            "Id": 142392021,
            "EpisodeMasterId": 142392,
            "Order": 1,
            "GroupOrder": 21,
            "SpeakerName": "初魅",
            "FontSize": 2,
            "Phrase": "それに……しぐれのご両親の言い分は至極真っ当だ。",
            "VoiceFileName": "1423920190",
            "CharacterMotions": [
                {
                    "slotNumber": 1,
                    "FacialExpressionMasterId": 107,
                    "BodyMotionMasterId": 13,
                    "LipSyncMasterId": 1,
                    "SpineId": 0,
                    "CharacterAppearanceType": 0,
                    "CharacterPosition": 2,
                    "CharacterLayerType": 1,
                    "SpineSize": 2
                },
                {
                    "slotNumber": 2,
                    "SpineId": 0,
                    "CharacterAppearanceType": 0,
                    "CharacterPosition": 4,
                    "CharacterLayerType": 1,
                    "SpineSize": 2
                }
            ],
            "SpeakerIconId": "201"
        },
        {
            "Id": 142392022,
            "EpisodeMasterId": 142392,
            "Order": 1,
            "GroupOrder": 22,
            "SpeakerName": "初魅",
            "FontSize": 2,
            "Phrase": "だからこそ、きちんと安心させて、/nなんの後顧の憂いもなく送り出して貰えることが、一番だと思ってな。",
            "VoiceFileName": "1423920200",
            "CharacterMotions": [
                {
                    "slotNumber": 1,
                    "FacialExpressionMasterId": 103,
                    "BodyMotionMasterId": 15,
                    "LipSyncMasterId": 1,
                    "SpineId": 0,
                    "CharacterAppearanceType": 0,
                    "CharacterPosition": 2,
                    "CharacterLayerType": 1,
                    "SpineSize": 2
                },
                {
                    "slotNumber": 2,
                    "SpineId": 0,
                    "CharacterAppearanceType": 0,
                    "CharacterPosition": 4,
                    "CharacterLayerType": 1,
                    "SpineSize": 2
                }
            ],
            "SpeakerIconId": "201"
        },
        {
            "Id": 142392023,
            "EpisodeMasterId": 142392,
            "Order": 1,
            "GroupOrder": 23,
            "SpeakerName": "容",
            "FontSize": 2,
            "Phrase": "それって、自分の両親とも重ねてる？/n劇団に入ることで、心配を掛けただろうって。",
            "VoiceFileName": "1423920210",
            "CharacterMotions": [
                {
                    "slotNumber": 1,
                    "SpineId": 0,
                    "CharacterAppearanceType": 0,
                    "CharacterPosition": 2,
                    "CharacterLayerType": 1,
                    "SpineSize": 2
                },
                {
                    "slotNumber": 2,
                    "FacialExpressionMasterId": 102,
                    "BodyMotionMasterId": 11,
                    "LipSyncMasterId": 4,
                    "SpineId": 0,
                    "CharacterAppearanceType": 0,
                    "CharacterPosition": 4,
                    "CharacterLayerType": 1,
                    "SpineSize": 2
                }
            ],
            "SpeakerIconId": "204"
        },
        {
            "Id": 142392024,
            "EpisodeMasterId": 142392,
            "Order": 1,
            "GroupOrder": 24,
            "SpeakerName": "初魅",
            "FontSize": 2,
            "Phrase": "まぁな。私の両親は応援して送り出してくれたが、/n思う所がなかったわけではないだろう。",
            "VoiceFileName": "1423920220",
            "CharacterMotions": [
                {
                    "slotNumber": 1,
                    "FacialExpressionMasterId": 201,
                    "BodyMotionMasterId": 15,
                    "LipSyncMasterId": 1,
                    "SpineId": 0,
                    "CharacterAppearanceType": 0,
                    "CharacterPosition": 2,
                    "CharacterLayerType": 1,
                    "SpineSize": 2
                },
                {
                    "slotNumber": 2,
                    "SpineId": 0,
                    "CharacterAppearanceType": 0,
                    "CharacterPosition": 4,
                    "CharacterLayerType": 1,
                    "SpineSize": 2
                }
            ],
            "SpeakerIconId": "201"
        },
        {
            "Id": 142392025,
            "EpisodeMasterId": 142392,
            "Order": 1,
            "GroupOrder": 25,
            "SpeakerName": "容",
            "FontSize": 2,
            "Phrase": "ま、そうだよね。それはアタシの家もそうかな。/n演劇について応援はしてくれてるけど……心配は絶対にあるはずだから。",
            "VoiceFileName": "1423920230",
            "CharacterMotions": [
                {
                    "slotNumber": 1,
                    "SpineId": 0,
                    "CharacterAppearanceType": 0,
                    "CharacterPosition": 2,
                    "CharacterLayerType": 1,
                    "SpineSize": 2
                },
                {
                    "slotNumber": 2,
                    "FacialExpressionMasterId": 105,
                    "BodyMotionMasterId": 6,
                    "LipSyncMasterId": 1,
                    "SpineId": 0,
                    "CharacterAppearanceType": 0,
                    "CharacterPosition": 4,
                    "CharacterLayerType": 1,
                    "SpineSize": 2
                }
            ],
            "SpeakerIconId": "204"
        },
        {
            "Id": 142392026,
            "EpisodeMasterId": 142392,
            "Order": 1,
            "GroupOrder": 26,
            "SpeakerName": "初魅",
            "FontSize": 2,
            "Phrase": "ならば、自分たちの為にも、/n尚のこと、次の公演では素晴らしい実績を残さなくてはな。",
            "VoiceFileName": "1423920240",
            "CharacterMotions": [
                {
                    "slotNumber": 1,
                    "FacialExpressionMasterId": 103,
                    "BodyMotionMasterId": 21,
                    "LipSyncMasterId": 1,
                    "SpineId": 0,
                    "CharacterAppearanceType": 0,
                    "CharacterPosition": 2,
                    "CharacterLayerType": 1,
                    "SpineSize": 2
                },
                {
                    "slotNumber": 2,
                    "SpineId": 0,
                    "CharacterAppearanceType": 0,
                    "CharacterPosition": 4,
                    "CharacterLayerType": 1,
                    "SpineSize": 2
                }
            ],
            "SpeakerIconId": "201"
        },
        {
            "Id": 142392027,
            "EpisodeMasterId": 142392,
            "Order": 1,
            "GroupOrder": 27,
            "SpeakerName": "容",
            "FontSize": 2,
            "Phrase": "うん、そうだね。/nそれがアタシたち自身……ひいてはEdenの為にもなるんだから。",
            "VoiceFileName": "1423920250",
            "CharacterMotions": [
                {
                    "slotNumber": 1,
                    "SpineId": 0,
                    "CharacterAppearanceType": 0,
                    "CharacterPosition": 2,
                    "CharacterLayerType": 1,
                    "SpineSize": 2
                },
                {
                    "slotNumber": 2,
                    "FacialExpressionMasterId": 71,
                    "HeadMotionMasterId": 1,
                    "BodyMotionMasterId": 13,
                    "LipSyncMasterId": 1,
                    "SpineId": 0,
                    "CharacterAppearanceType": 0,
                    "CharacterPosition": 4,
                    "CharacterLayerType": 1,
                    "SpineSize": 2
                }
            ],
            "SpeakerIconId": "204"
        },
        {
            "Id": 142392028,
            "EpisodeMasterId": 142392,
            "Order": 1,
            "GroupOrder": 28,
            "SpeakerName": "初魅",
            "FontSize": 2,
            "Phrase": "ああ……お前たちの居場所は私が作り続けるさ。/n我がEdenは、皆の為の楽園でもあるからな。",
            "VoiceFileName": "1423920260",
            "CharacterMotions": [
                {
                    "slotNumber": 1,
                    "BodyMotionMasterId": 3,
                    "LipSyncMasterId": 1,
                    "SpineId": 0,
                    "CharacterAppearanceType": 0,
                    "CharacterPosition": 2,
                    "CharacterLayerType": 1,
                    "SpineSize": 2
                },
                {
                    "slotNumber": 2,
                    "SpineId": 0,
                    "CharacterAppearanceType": 0,
                    "CharacterPosition": 4,
                    "CharacterLayerType": 1,
                    "SpineSize": 2
                }
            ],
            "SpeakerIconId": "201"
        },
        {
            "Id": 142392029,
            "EpisodeMasterId": 142392,
            "Order": 1,
            "GroupOrder": 29,
            "SpeakerName": "初魅",
            "FontSize": 2,
            "Phrase": "（その為にも、次の公演……絶対に成功へと導いてみせる）",
            "VoiceFileName": "1423920270",
            "CharacterMotions": [
                {
                    "slotNumber": 1,
                    "FacialExpressionMasterId": 101,
                    "BodyMotionMasterId": 15,
                    "SpineId": 0,
                    "CharacterAppearanceType": 0,
                    "CharacterPosition": 3,
                    "CharacterLayerType": 1,
                    "SpineSize": 2
                }
            ],
            "SpeakerIconId": "201"
        }
    ]
}