{
    "EpisodeId": 2007103,
    "StoryType": 2,
    "Order": 3,
    "Prev": 2007102,
    "Next": 2007104,
    "Chapter": "Stella Generalprobe!",
    "Title": "手を取り合って",
    "EpisodeDetail": [
        {
            "Id": 2007103001,
            "EpisodeMasterId": 2007103,
            "Order": 1,
            "GroupOrder": 1,
            "SpeakerName": "ここな",
            "FontSize": 2,
            "Phrase": "あ、この童話！　最近話題なんだよ。/nテレビでも紹介されてたんだ～。",
            "BackgroundImageFileName": "280",
            "BgmFileName": "102",
            "VoiceFileName": "20071030010",
            "CharacterMotions": [
                {
                    "slotNumber": 1,
                    "FacialExpressionMasterId": 103,
                    "BodyMotionMasterId": 20,
                    "LipSyncMasterId": 1,
                    "SpineId": 10101,
                    "CharacterAppearanceType": 0,
                    "CharacterPosition": 3,
                    "CharacterLayerType": 1,
                    "SpineSize": 2
                }
            ],
            "SpeakerIconId": "101"
        },
        {
            "Id": 2007103002,
            "EpisodeMasterId": 2007103,
            "Order": 1,
            "GroupOrder": 2,
            "SpeakerName": "静香",
            "FontSize": 2,
            "Phrase": "へぇ～、表紙が猫なのね。可愛いじゃない。/nどういう話なの？",
            "VoiceFileName": "20071030020",
            "CharacterMotions": [
                {
                    "slotNumber": 1,
                    "SpineId": 0,
                    "CharacterAppearanceType": 0,
                    "CharacterPosition": 2,
                    "CharacterLayerType": 1,
                    "SpineSize": 2
                },
                {
                    "slotNumber": 2,
                    "FacialExpressionMasterId": 102,
                    "BodyMotionMasterId": 11,
                    "LipSyncMasterId": 4,
                    "SpineId": 10201,
                    "CharacterAppearanceType": 0,
                    "CharacterPosition": 4,
                    "CharacterLayerType": 1,
                    "SpineSize": 2
                }
            ],
            "SpeakerIconId": "102"
        },
        {
            "Id": 2007103003,
            "EpisodeMasterId": 2007103,
            "Order": 1,
            "GroupOrder": 3,
            "SpeakerName": "ここな",
            "FontSize": 2,
            "Phrase": "これはね、昼寝をしていた猫が夢の中で、/n航海の旅に出る話で……。",
            "VoiceFileName": "20071030030",
            "CharacterMotions": [
                {
                    "slotNumber": 1,
                    "FacialExpressionMasterId": 103,
                    "BodyMotionMasterId": 7,
                    "LipSyncMasterId": 1,
                    "SpineId": 0,
                    "CharacterAppearanceType": 0,
                    "CharacterPosition": 2,
                    "CharacterLayerType": 1,
                    "SpineSize": 2
                },
                {
                    "slotNumber": 2,
                    "SpineId": 10201,
                    "CharacterAppearanceType": 0,
                    "CharacterPosition": 4,
                    "CharacterLayerType": 1,
                    "SpineSize": 2
                }
            ],
            "SpeakerIconId": "101"
        },
        {
            "Id": 2007103004,
            "EpisodeMasterId": 2007103,
            "Order": 1,
            "GroupOrder": 4,
            "FontSize": 2,
            "Phrase": "",
            "BackgroundImageFileName": "120",
            "BackgroundImageFileFadeType": 1,
            "CharacterMotions": [],
            "FadeValue1": 0.20000000298023224,
            "FadeValue2": 0.30000001192092896,
            "FadeValue3": 0.20000000298023224
        },
        {
            "Id": 2007103005,
            "EpisodeMasterId": 2007103,
            "Order": 1,
            "GroupOrder": 5,
            "SpeakerName": "ここな",
            "FontSize": 2,
            "Phrase": "ここって正月に流石ちゃんたちと一緒に来たお餅屋さんだよね？",
            "VoiceFileName": "20071030040",
            "CharacterMotions": [
                {
                    "slotNumber": 1,
                    "FacialExpressionMasterId": 103,
                    "BodyMotionMasterId": 11,
                    "LipSyncMasterId": 1,
                    "SpineId": 10101,
                    "CharacterAppearanceType": 0,
                    "CharacterPosition": 3,
                    "CharacterLayerType": 1,
                    "SpineSize": 2
                }
            ],
            "SpeakerIconId": "101"
        },
        {
            "Id": 2007103006,
            "EpisodeMasterId": 2007103,
            "Order": 1,
            "GroupOrder": 6,
            "SpeakerName": "静香",
            "FontSize": 2,
            "Phrase": "そうね……って、見てここな！",
            "VoiceFileName": "20071030050",
            "CharacterMotions": [
                {
                    "slotNumber": 1,
                    "SpineId": 0,
                    "CharacterAppearanceType": 0,
                    "CharacterPosition": 2,
                    "CharacterLayerType": 1,
                    "SpineSize": 2
                },
                {
                    "slotNumber": 2,
                    "FacialExpressionMasterId": 500,
                    "BodyMotionMasterId": 13,
                    "LipSyncMasterId": 1,
                    "SpineId": 10201,
                    "CharacterAppearanceType": 0,
                    "CharacterPosition": 4,
                    "CharacterLayerType": 1,
                    "SpineSize": 2
                }
            ],
            "SpeakerIconId": "102"
        },
        {
            "Id": 2007103007,
            "EpisodeMasterId": 2007103,
            "Order": 1,
            "GroupOrder": 7,
            "SpeakerName": "ここな",
            "FontSize": 2,
            "Phrase": "どうしたの？　そんな目を見開いて……えっ！？",
            "VoiceFileName": "20071030060",
            "CharacterMotions": [
                {
                    "slotNumber": 1,
                    "FacialExpressionMasterId": 102,
                    "BodyMotionMasterId": 20,
                    "LipSyncMasterId": 4,
                    "SpineId": 0,
                    "CharacterAppearanceType": 0,
                    "CharacterPosition": 2,
                    "CharacterLayerType": 1,
                    "SpineSize": 2
                },
                {
                    "slotNumber": 2,
                    "SpineId": 10201,
                    "CharacterAppearanceType": 0,
                    "CharacterPosition": 4,
                    "CharacterLayerType": 1,
                    "SpineSize": 2
                }
            ],
            "SpeakerIconId": "101"
        },
        {
            "Id": 2007103008,
            "EpisodeMasterId": 2007103,
            "Order": 1,
            "GroupOrder": 8,
            "SpeakerName": "ここな・静香",
            "FontSize": 2,
            "Phrase": "そうめん……もち！？",
            "VoiceFileName": "20071030070",
            "CharacterMotions": [
                {
                    "slotNumber": 1,
                    "FacialExpressionMasterId": 500,
                    "BodyMotionMasterId": 5,
                    "LipSyncMasterId": 1,
                    "SpineId": 0,
                    "CharacterAppearanceType": 0,
                    "CharacterPosition": 2,
                    "CharacterLayerType": 1,
                    "SpineSize": 2
                },
                {
                    "slotNumber": 2,
                    "FacialExpressionMasterId": 500,
                    "BodyMotionMasterId": 5,
                    "LipSyncMasterId": 1,
                    "SpineId": 10201,
                    "CharacterAppearanceType": 0,
                    "CharacterPosition": 4,
                    "CharacterLayerType": 1,
                    "SpineSize": 2
                }
            ],
            "SpeakerIconId": "1"
        },
        {
            "Id": 2007103009,
            "EpisodeMasterId": 2007103,
            "Order": 1,
            "GroupOrder": 9,
            "FontSize": 2,
            "Phrase": "",
            "BackgroundImageFileName": "270",
            "BackgroundImageFileFadeType": 1,
            "CharacterMotions": [],
            "FadeValue1": 0.20000000298023224,
            "FadeValue2": 0.30000001192092896,
            "FadeValue3": 0.20000000298023224
        },
        {
            "Id": 2007103010,
            "EpisodeMasterId": 2007103,
            "Order": 1,
            "GroupOrder": 10,
            "SpeakerName": "ここな",
            "FontSize": 2,
            "Phrase": "いやー、色々買ったね～。",
            "VoiceFileName": "20071030080",
            "CharacterMotions": [
                {
                    "slotNumber": 1,
                    "FacialExpressionMasterId": 71,
                    "BodyMotionMasterId": 20,
                    "LipSyncMasterId": 1,
                    "SpineId": 10101,
                    "CharacterAppearanceType": 0,
                    "CharacterPosition": 3,
                    "CharacterLayerType": 1,
                    "SpineSize": 2
                }
            ],
            "SpeakerIconId": "101"
        },
        {
            "Id": 2007103011,
            "EpisodeMasterId": 2007103,
            "Order": 1,
            "GroupOrder": 11,
            "SpeakerName": "静香",
            "FontSize": 2,
            "Phrase": "そうね。……ちょっと疲れちゃったわね。/nそこのベンチに座りましょうか。",
            "VoiceFileName": "20071030090",
            "CharacterMotions": [
                {
                    "slotNumber": 1,
                    "SpineId": 0,
                    "CharacterAppearanceType": 0,
                    "CharacterPosition": 2,
                    "CharacterLayerType": 1,
                    "SpineSize": 2
                },
                {
                    "slotNumber": 2,
                    "FacialExpressionMasterId": 103,
                    "BodyMotionMasterId": 15,
                    "LipSyncMasterId": 1,
                    "SpineId": 10201,
                    "CharacterAppearanceType": 0,
                    "CharacterPosition": 4,
                    "CharacterLayerType": 1,
                    "SpineSize": 2
                }
            ],
            "SpeakerIconId": "102"
        },
        {
            "Id": 2007103012,
            "EpisodeMasterId": 2007103,
            "Order": 1,
            "GroupOrder": 12,
            "SpeakerName": "ここな",
            "FontSize": 2,
            "Phrase": "そうだね。",
            "VoiceFileName": "20071030100",
            "CharacterMotions": [
                {
                    "slotNumber": 1,
                    "FacialExpressionMasterId": 103,
                    "BodyMotionMasterId": 13,
                    "LipSyncMasterId": 1,
                    "SpineId": 0,
                    "CharacterAppearanceType": 0,
                    "CharacterPosition": 2,
                    "CharacterLayerType": 1,
                    "SpineSize": 2
                },
                {
                    "slotNumber": 2,
                    "SpineId": 10201,
                    "CharacterAppearanceType": 0,
                    "CharacterPosition": 4,
                    "CharacterLayerType": 1,
                    "SpineSize": 2
                }
            ],
            "SpeakerIconId": "101"
        },
        {
            "Id": 2007103013,
            "EpisodeMasterId": 2007103,
            "Order": 1,
            "GroupOrder": 13,
            "SpeakerName": "静香",
            "FontSize": 2,
            "Phrase": "よいしょっと……。",
            "VoiceFileName": "20071030110",
            "CharacterMotions": [
                {
                    "slotNumber": 1,
                    "SpineId": 0,
                    "CharacterAppearanceType": 0,
                    "CharacterPosition": 2,
                    "CharacterLayerType": 1,
                    "SpineSize": 2
                },
                {
                    "slotNumber": 2,
                    "FacialExpressionMasterId": 71,
                    "BodyMotionMasterId": 13,
                    "LipSyncMasterId": 1,
                    "SpineId": 10201,
                    "CharacterAppearanceType": 0,
                    "CharacterPosition": 4,
                    "CharacterLayerType": 1,
                    "SpineSize": 2
                }
            ],
            "SpeakerIconId": "102"
        },
        {
            "Id": 2007103014,
            "EpisodeMasterId": 2007103,
            "Order": 1,
            "GroupOrder": 14,
            "FontSize": 2,
            "Phrase": "",
            "BackgroundImageFileFadeType": 1,
            "CharacterMotions": [],
            "FadeValue1": 0.20000000298023224,
            "FadeValue2": 0.30000001192092896,
            "FadeValue3": 0.20000000298023224
        },
        {
            "Id": 2007103015,
            "EpisodeMasterId": 2007103,
            "Order": 1,
            "GroupOrder": 15,
            "SpeakerName": "ここな",
            "FontSize": 2,
            "Phrase": "ふぅ～……なんだか久しぶりだよね。/nこうして静香ちゃんとふたりきりで出かけるなんて。",
            "VoiceFileName": "20071030120",
            "CharacterMotions": [
                {
                    "slotNumber": 1,
                    "FacialExpressionMasterId": 71,
                    "BodyMotionMasterId": 20,
                    "LipSyncMasterId": 1,
                    "SpineId": 10101,
                    "CharacterAppearanceType": 0,
                    "CharacterPosition": 3,
                    "CharacterLayerType": 1,
                    "SpineSize": 2
                }
            ],
            "SpeakerIconId": "101"
        },
        {
            "Id": 2007103016,
            "EpisodeMasterId": 2007103,
            "Order": 1,
            "GroupOrder": 16,
            "SpeakerName": "静香",
            "FontSize": 2,
            "Phrase": "そうね。……そう考えると、なんだか不思議かも。/n実家に居る頃はふたりで居ることが当たり前だったのに。",
            "VoiceFileName": "20071030130",
            "CharacterMotions": [
                {
                    "slotNumber": 1,
                    "SpineId": 0,
                    "CharacterAppearanceType": 0,
                    "CharacterPosition": 2,
                    "CharacterLayerType": 1,
                    "SpineSize": 2
                },
                {
                    "slotNumber": 2,
                    "FacialExpressionMasterId": 105,
                    "BodyMotionMasterId": 15,
                    "LipSyncMasterId": 1,
                    "SpineId": 10201,
                    "CharacterAppearanceType": 0,
                    "CharacterPosition": 4,
                    "CharacterLayerType": 1,
                    "SpineSize": 2
                }
            ],
            "SpeakerIconId": "102"
        },
        {
            "Id": 2007103017,
            "EpisodeMasterId": 2007103,
            "Order": 1,
            "GroupOrder": 17,
            "SpeakerName": "ここな",
            "FontSize": 2,
            "Phrase": "そうだね、海で一緒に演技をして……。",
            "VoiceFileName": "20071030140",
            "CharacterMotions": [
                {
                    "slotNumber": 1,
                    "FacialExpressionMasterId": 103,
                    "BodyMotionMasterId": 6,
                    "LipSyncMasterId": 1,
                    "SpineId": 0,
                    "CharacterAppearanceType": 0,
                    "CharacterPosition": 2,
                    "CharacterLayerType": 1,
                    "SpineSize": 2
                },
                {
                    "slotNumber": 2,
                    "SpineId": 10201,
                    "CharacterAppearanceType": 0,
                    "CharacterPosition": 4,
                    "CharacterLayerType": 1,
                    "SpineSize": 2
                }
            ],
            "SpeakerIconId": "101"
        },
        {
            "Id": 2007103018,
            "EpisodeMasterId": 2007103,
            "Order": 1,
            "GroupOrder": 18,
            "SpeakerName": "静香",
            "FontSize": 2,
            "Phrase": "こっちに来てもカトリナたちと打ち解け合うまでは、/n私とふたりでずっと演技の練習してたし。",
            "VoiceFileName": "20071030150",
            "CharacterMotions": [
                {
                    "slotNumber": 1,
                    "SpineId": 0,
                    "CharacterAppearanceType": 0,
                    "CharacterPosition": 2,
                    "CharacterLayerType": 1,
                    "SpineSize": 2
                },
                {
                    "slotNumber": 2,
                    "FacialExpressionMasterId": 103,
                    "BodyMotionMasterId": 13,
                    "LipSyncMasterId": 1,
                    "SpineId": 10201,
                    "CharacterAppearanceType": 0,
                    "CharacterPosition": 4,
                    "CharacterLayerType": 1,
                    "SpineSize": 2
                }
            ],
            "SpeakerIconId": "102"
        },
        {
            "Id": 2007103019,
            "EpisodeMasterId": 2007103,
            "Order": 1,
            "GroupOrder": 19,
            "SpeakerName": "静香",
            "FontSize": 2,
            "Phrase": "今ではここなひとりでも演技の練習が出来るし、/nシリウスのみんなと稽古をするのも当たり前だものね",
            "VoiceFileName": "20071030160",
            "CharacterMotions": [
                {
                    "slotNumber": 1,
                    "SpineId": 0,
                    "CharacterAppearanceType": 0,
                    "CharacterPosition": 2,
                    "CharacterLayerType": 1,
                    "SpineSize": 2
                },
                {
                    "slotNumber": 2,
                    "FacialExpressionMasterId": 71,
                    "LipSyncMasterId": 1,
                    "SpineId": 10201,
                    "CharacterAppearanceType": 0,
                    "CharacterPosition": 4,
                    "CharacterLayerType": 1,
                    "SpineSize": 2
                }
            ],
            "SpeakerIconId": "102"
        },
        {
            "Id": 2007103020,
            "EpisodeMasterId": 2007103,
            "Order": 1,
            "GroupOrder": 20,
            "SpeakerName": "ここな",
            "FontSize": 2,
            "Phrase": "それも凄いよね、昔は入団試験に落ちてばっかりだったのに。",
            "VoiceFileName": "20071030170",
            "CharacterMotions": [
                {
                    "slotNumber": 1,
                    "FacialExpressionMasterId": 200,
                    "BodyMotionMasterId": 20,
                    "LipSyncMasterId": 1,
                    "SpineId": 0,
                    "CharacterAppearanceType": 0,
                    "CharacterPosition": 2,
                    "CharacterLayerType": 1,
                    "SpineSize": 2
                },
                {
                    "slotNumber": 2,
                    "SpineId": 10201,
                    "CharacterAppearanceType": 0,
                    "CharacterPosition": 4,
                    "CharacterLayerType": 1,
                    "SpineSize": 2
                }
            ],
            "SpeakerIconId": "101"
        },
        {
            "Id": 2007103021,
            "EpisodeMasterId": 2007103,
            "Order": 1,
            "GroupOrder": 21,
            "SpeakerName": "静香",
            "FontSize": 2,
            "Phrase": "今じゃ、シリウスのみんなと世界演劇リーグの舞台に、/n立とうとしてるのよね……。",
            "VoiceFileName": "20071030180",
            "CharacterMotions": [
                {
                    "slotNumber": 1,
                    "SpineId": 0,
                    "CharacterAppearanceType": 0,
                    "CharacterPosition": 2,
                    "CharacterLayerType": 1,
                    "SpineSize": 2
                },
                {
                    "slotNumber": 2,
                    "FacialExpressionMasterId": 103,
                    "BodyMotionMasterId": 15,
                    "LipSyncMasterId": 1,
                    "SpineId": 10201,
                    "CharacterAppearanceType": 0,
                    "CharacterPosition": 4,
                    "CharacterLayerType": 1,
                    "SpineSize": 2
                }
            ],
            "SpeakerIconId": "102"
        },
        {
            "Id": 2007103022,
            "EpisodeMasterId": 2007103,
            "Order": 1,
            "GroupOrder": 22,
            "SpeakerName": "静香",
            "FontSize": 2,
            "Phrase": "昔の自分に言っても信じてくれるか……。",
            "VoiceFileName": "20071030190",
            "CharacterMotions": [
                {
                    "slotNumber": 1,
                    "SpineId": 0,
                    "CharacterAppearanceType": 0,
                    "CharacterPosition": 2,
                    "CharacterLayerType": 1,
                    "SpineSize": 2
                },
                {
                    "slotNumber": 2,
                    "FacialExpressionMasterId": 71,
                    "BodyMotionMasterId": 4,
                    "LipSyncMasterId": 1,
                    "SpineId": 10201,
                    "CharacterAppearanceType": 0,
                    "CharacterPosition": 4,
                    "CharacterLayerType": 1,
                    "SpineSize": 2
                }
            ],
            "SpeakerIconId": "102"
        },
        {
            "Id": 2007103023,
            "EpisodeMasterId": 2007103,
            "Order": 1,
            "GroupOrder": 23,
            "SpeakerName": "ここな",
            "FontSize": 2,
            "Phrase": "だね～。昔の私に言っても、/nきっと驚いて信じないかも……。",
            "VoiceFileName": "20071030200",
            "CharacterMotions": [
                {
                    "slotNumber": 1,
                    "FacialExpressionMasterId": 202,
                    "HeadMotionMasterId": 1,
                    "BodyMotionMasterId": 13,
                    "LipSyncMasterId": 1,
                    "SpineId": 0,
                    "CharacterAppearanceType": 0,
                    "CharacterPosition": 2,
                    "CharacterLayerType": 1,
                    "SpineSize": 2
                },
                {
                    "slotNumber": 2,
                    "SpineId": 10201,
                    "CharacterAppearanceType": 0,
                    "CharacterPosition": 4,
                    "CharacterLayerType": 1,
                    "SpineSize": 2
                }
            ],
            "SpeakerIconId": "101"
        },
        {
            "Id": 2007103024,
            "EpisodeMasterId": 2007103,
            "Order": 1,
            "GroupOrder": 24,
            "SpeakerName": "ここな",
            "FontSize": 2,
            "Phrase": "……私たちここまで来たんだね。",
            "VoiceFileName": "20071030210",
            "CharacterMotions": [
                {
                    "slotNumber": 1,
                    "FacialExpressionMasterId": 103,
                    "LipSyncMasterId": 1,
                    "SpineId": 0,
                    "CharacterAppearanceType": 0,
                    "CharacterPosition": 2,
                    "CharacterLayerType": 1,
                    "SpineSize": 2
                },
                {
                    "slotNumber": 2,
                    "SpineId": 10201,
                    "CharacterAppearanceType": 0,
                    "CharacterPosition": 4,
                    "CharacterLayerType": 1,
                    "SpineSize": 2
                }
            ],
            "SpeakerIconId": "101"
        },
        {
            "Id": 2007103025,
            "EpisodeMasterId": 2007103,
            "Order": 1,
            "GroupOrder": 25,
            "SpeakerName": "静香",
            "FontSize": 2,
            "Phrase": "ふふっ、ゴールしたみたいに言っちゃって。/nまだまだ上に行く……そうでしょ？",
            "VoiceFileName": "20071030220",
            "CharacterMotions": [
                {
                    "slotNumber": 1,
                    "SpineId": 0,
                    "CharacterAppearanceType": 0,
                    "CharacterPosition": 2,
                    "CharacterLayerType": 1,
                    "SpineSize": 2
                },
                {
                    "slotNumber": 2,
                    "FacialExpressionMasterId": 202,
                    "BodyMotionMasterId": 11,
                    "LipSyncMasterId": 1,
                    "SpineId": 10201,
                    "CharacterAppearanceType": 0,
                    "CharacterPosition": 4,
                    "CharacterLayerType": 1,
                    "SpineSize": 2
                }
            ],
            "SpeakerIconId": "102"
        },
        {
            "Id": 2007103026,
            "EpisodeMasterId": 2007103,
            "Order": 1,
            "GroupOrder": 26,
            "SpeakerName": "静香",
            "FontSize": 2,
            "Phrase": "ワールドダイスターはおろか、/n八恵ちゃんみたいなダイスターにもまだなれてないんだから。",
            "VoiceFileName": "20071030230",
            "CharacterMotions": [
                {
                    "slotNumber": 1,
                    "SpineId": 0,
                    "CharacterAppearanceType": 0,
                    "CharacterPosition": 2,
                    "CharacterLayerType": 1,
                    "SpineSize": 2
                },
                {
                    "slotNumber": 2,
                    "FacialExpressionMasterId": 103,
                    "BodyMotionMasterId": 15,
                    "LipSyncMasterId": 1,
                    "SpineId": 10201,
                    "CharacterAppearanceType": 0,
                    "CharacterPosition": 4,
                    "CharacterLayerType": 1,
                    "SpineSize": 2
                }
            ],
            "SpeakerIconId": "102"
        },
        {
            "Id": 2007103027,
            "EpisodeMasterId": 2007103,
            "Order": 1,
            "GroupOrder": 27,
            "SpeakerName": "静香",
            "FontSize": 2,
            "Phrase": "目指してるんでしょ？",
            "VoiceFileName": "20071030240",
            "CharacterMotions": [
                {
                    "slotNumber": 1,
                    "SpineId": 0,
                    "CharacterAppearanceType": 0,
                    "CharacterPosition": 2,
                    "CharacterLayerType": 1,
                    "SpineSize": 2
                },
                {
                    "slotNumber": 2,
                    "FacialExpressionMasterId": 103,
                    "BodyMotionMasterId": 11,
                    "LipSyncMasterId": 1,
                    "SpineId": 10201,
                    "CharacterAppearanceType": 0,
                    "CharacterPosition": 4,
                    "CharacterLayerType": 1,
                    "SpineSize": 2
                }
            ],
            "SpeakerIconId": "102"
        },
        {
            "Id": 2007103028,
            "EpisodeMasterId": 2007103,
            "Order": 1,
            "GroupOrder": 28,
            "SpeakerName": "ここな",
            "FontSize": 2,
            "Phrase": "……うん！　そうだね。/nこれからも、一緒に頑張ろうね……静香ちゃん！",
            "VoiceFileName": "20071030250",
            "CharacterMotions": [
                {
                    "slotNumber": 1,
                    "FacialExpressionMasterId": 103,
                    "BodyMotionMasterId": 20,
                    "LipSyncMasterId": 1,
                    "SpineId": 0,
                    "CharacterAppearanceType": 0,
                    "CharacterPosition": 2,
                    "CharacterLayerType": 1,
                    "SpineSize": 2
                },
                {
                    "slotNumber": 2,
                    "SpineId": 10201,
                    "CharacterAppearanceType": 0,
                    "CharacterPosition": 4,
                    "CharacterLayerType": 1,
                    "SpineSize": 2
                }
            ],
            "SpeakerIconId": "101"
        },
        {
            "Id": 2007103029,
            "EpisodeMasterId": 2007103,
            "Order": 1,
            "GroupOrder": 29,
            "SpeakerName": "静香",
            "FontSize": 2,
            "Phrase": "ええ！　まずは世界演劇リーグ。/nそのコンテストで、良い演技を見せましょう。",
            "BackgroundCharacterImageFileName": "142480_0",
            "VoiceFileName": "20071030260",
            "CharacterMotions": [],
            "SpeakerIconId": "102"
        },
        {
            "Id": 2007103030,
            "EpisodeMasterId": 2007103,
            "Order": 1,
            "GroupOrder": 30,
            "SpeakerName": "ここな",
            "FontSize": 2,
            "Phrase": "うん！　また、明日から頑張らないとだね！",
            "BackgroundCharacterImageFileName": "142480_0",
            "VoiceFileName": "20071030270",
            "CharacterMotions": [],
            "SpeakerIconId": "101"
        }
    ]
}