{
    "EpisodeId": 231040,
    "StoryType": 5,
    "Title": "軍神はかく語れり",
    "EpisodeDetail": [
        {
            "Id": 23104001,
            "EpisodeType": 0,
            "CharacterId": null,
            "Description": "「軍神はかく語れり」/n配役/n軍神アレース：カトリナ・グリーベル/nアポロン：鳳 ここな/nアルテミス：静香/nガニュメデス：流石 知冴",
            "Order": 1
        },
        {
            "Id": 23104102,
            "EpisodeType": 1,
            "CharacterId": null,
            "Description": "「軍神はかく語れり」/n■第一幕/n空は煤け、大地は血と鉄の匂いに満ちていた。/n舞台は、数多の神々や英雄が入り乱れる古代の戦場。/nアレースは黄金の鎧を身に纏い、手には天を突くほどの大槍を握りしめている。/n/n彼はかつて、数千の兵をたった一人で壊滅させた「伝説の戦い」を振り返る。/n対峙するのは、傲慢な王が率いる精鋭のファランクス。/n神を敬わず、聖域にて唾を吐いた不届き者。/n彼らは「神などなにするものぞ」と豪語し、盾の壁を築いてアレースを包囲する。/n/nしかし、アレースは嘲笑う。/n「愚かだな……お前たちが身を置く戦い！/n　お前たちの仲間の命を奪った戦いの化身こそが私なのだ！！」/n/n彼が一歩踏み出すごとに大地は鳴動し、大気の温度は跳ね上がる。/nアレースが槍を水平に構えると、その穂先から戦意の奔流が溢れ出し、周囲の空間を赤く染め上げた。",
            "Order": 2
        },
        {
            "Id": 23104203,
            "EpisodeType": 2,
            "CharacterId": null,
            "Description": "「軍神はかく語れり」/n■第二幕/nいよいよ戦いの火蓋が切って落とされる。/nアレースは槍を風車のように振り回し、迫り来る無数の矢を平然と叩き落とす。/n盾の壁へと突撃した彼は大槍の一突きで重厚な銅の盾を紙細工のように貫き、/nそのまま敵の陣形を内部から食い破っていく。/n/n槍を振るう動作は、暴力的なまでの美しさを湛えていた。/n突き、払い、叩きつける。/nその一挙手一投足が破壊の旋律を奏で、敵軍の兵士たちは恐怖に震え上がった。/n槍が折れればアレースは腰の長剣を抜き放ち、残光が走るような鋭い剣筋で敵を圧倒する。/n/n「恐怖よ、敵の心に巣食え！　 逃げ惑う背こそが戦場の華！」/n/nアレースの咆哮が戦場に響き渡ると、敵軍は総崩れとなった。/n/n城壁に逃げ込む兵士たち。/n逃れられた……そう一息ついたのも束の間、ギギギと張り詰めた音が聞こえる。/n/n城壁の上から見れば、弓の弦を引いてギリギリと張り詰め、/n城壁に狙いを定めるアレースの姿。/n/n「そのようなあばら屋……吹き飛ばしてくれる！」/n/nそう言うと、張り詰めた弦から指を放す。/nその瞬間、耳をつんざく風切り音。/n/nそして直後、嵐が訪れたかのように、/n数多の兵士が城壁ごと吹き飛ばされて、叫びをあげた。/n/n彼は傷一つ負うことなく、ただ一人、累々と築かれた兵の山の上に立ち尽くす。/n夕陽を背に浴びた彼の姿は、一枚の絵のように厳かであったという。",
            "Order": 3
        },
        {
            "Id": 23104304,
            "EpisodeType": 3,
            "CharacterId": null,
            "Description": "「軍神はかく語れり」/n■第三幕/n戦いは終結した。/nアレースは膝をつき許しを請う敵軍の将軍を見下ろしながら、ゆっくりと剣を鞘に収める。彼は略奪や虐殺に興味があるのではない。/nただ自身の武勇が絶対であり、戦場という極限状態において誰よりも輝く存在であることを証明したに過ぎないのだ。/n/n王は平伏し、これまでの神への不敬を懺悔した。/nアレースはそれを見て、良しとした。/n/n「これこそが勝利だ。圧倒的な戦力による制圧。/n　ただ正面から敵を叩き潰す力……それこそが戦を支配する」/n/n彼は天を仰ぎ、勝利を祝う勝鬨を上げる。/nその声は雲を散らし、オリンポスの頂まで届かんばかりの勢いを持っていた。",
            "Order": 4
        },
        {
            "Id": 23104405,
            "EpisodeType": 4,
            "CharacterId": null,
            "Description": "「軍神はかく語れり」/n■第四幕/n「……というわけだ。どうだガニュメデス、/n　私の武芸はいかなる神にも負けることのない伝説だろう？」/n/n場面は一転し、豪奢なオリンポスの宮殿へ。/nそこには自慢話をひとしきり終えて満足げに鼻を鳴らすアレースと、/n困ったような笑顔でネクタルを注ごうとする美少年ガニュメデスの姿があった。/nアレースのこれまでの「冒険活劇」は、神々の集いで繰り広げられた自慢話だったのである。/n/n「そうだな、アルテミスの腕は狩りにおいては確かに卓越している。/n　しかし、こと戦においては、狩猟の弓は通用しない」/n/n「やはり、この軍神アレースこそが、一番の弓の名手。/n　私こそが、もっとも弓を扱うに長けた神ということだっ！！」/n/n「なんだと……？　それは聞き捨てならないぞ、アレース！！」/n/nしたり顔で語るアレースに、睨みを利かせるアポロン。/n彼は優雅に髪をかき上げ、アレースを真っ向から見据える。/n/n「私の妹であれば、お前のように城壁に逃がす前に全てを撃ち抜いていた。/n　すべての兵がまるで射抜かれた兎のように横たわっていただろう！」/n/n「ふん……戦を知らぬ者の戯言よな、戦いとは狩猟とは違う。/n　あー、もうやめろ。これ以上口を開いてもバカがバレるだけだぞ」/n/n「バカはお前だ！　そもそも弓とは狩猟の道具！/n　戦の弓で弓を語るお前こそが不心得者なんだ！/n　私の妹の方が、粗野で野蛮なお前よりも優れているのは明白！」/n/n「ほう、吠えるではないか……！」/n/nアレースの眼光が鋭くなる、まるで鋭い槍の切っ先のように剣呑な光。/nアポロンもまた、自慢の妹を侮辱されたと捉え、そのことに苛立ちを隠さず、/n二神の間にはパチパチと物理的に火花が散り始めた。/n/nその様子を少し離れた席から眺めていたアルテミスは、深いため息をつく。/n（また始まったよ……。兄さんってば……）/n/nオロオロとするガニュメデスに同情の視線を送りつつ、苦笑いを浮かべる。/nその後二神の意地の張り合いが「双子の英雄を巻き込んだ弓術対決」へと発展し、/n最終的にガニュメデスにネクタルを振る舞う羽目になるとは、今の彼らはまだ知らない。/n/n「……今日は長い一日になりそうね」/n/nアルテミスは、呆れた様子で呟いた。",
            "Order": 5
        },
        {
            "Id": 23104506,
            "EpisodeType": 5,
            "CharacterId": 103,
            "Description": "おつかれさま。/nここな、静香。",
            "Order": 6
        },
        {
            "Id": 23104507,
            "EpisodeType": 5,
            "CharacterId": 101,
            "Description": "お疲れ様～、カトリナちゃん。",
            "Order": 7
        },
        {
            "Id": 23104508,
            "EpisodeType": 5,
            "CharacterId": 102,
            "Description": "お疲れ様、カトリナ。/nふふ、手応えありって感じね。",
            "Order": 8
        },
        {
            "Id": 23104509,
            "EpisodeType": 5,
            "CharacterId": 103,
            "Description": "それはこっちの台詞じゃない？/n静香もここなも良い顔してる。",
            "Order": 9
        },
        {
            "Id": 23104510,
            "EpisodeType": 5,
            "CharacterId": 101,
            "Description": "そうかな？えへへ……、/nでもやっぱりゲネプロがうまくいったら嬉しいよ。",
            "Order": 10
        },
        {
            "Id": 23104511,
            "EpisodeType": 5,
            "CharacterId": 102,
            "Description": "特に、世界演劇リーグの演目だと猶更ね。",
            "Order": 11
        },
        {
            "Id": 23104512,
            "EpisodeType": 5,
            "CharacterId": 103,
            "Description": "……これから立つのよね。/n良い舞台にしましょう。",
            "Order": 12
        },
        {
            "Id": 23104513,
            "EpisodeType": 5,
            "CharacterId": 101,
            "Description": "……！　うん！",
            "Order": 13
        },
        {
            "Id": 23104514,
            "EpisodeType": 5,
            "CharacterId": 102,
            "Description": "ええ、当然よ！",
            "Order": 14
        }
    ]
}